slink/__init__.py
slink/api.py
slink/decorators.py
slink_api-0.1.7.dist-info/METADATA
slink_api-0.1.7.dist-info/WHEEL
slink_api-0.1.7.dist-info/RECORD
