Metadata-Version: 2.1
Name: slink-api
Version: 0.1.7
Summary: Simple and expressive REST clients without the fuss
Home-page: https://github.com/james-allan-lloyd/slink
Author: James Lloyd
Author-email: james.allan.lloyd@gmail.com
Requires-Python: >=3.8,<4.0
Classifier: Programming Language :: Python :: 3
Classifier: Programming Language :: Python :: 3.8
Classifier: Programming Language :: Python :: 3.9
Classifier: Programming Language :: Python :: 3.10
Classifier: Programming Language :: Python :: 3.11
Requires-Dist: pydantic (>=1.10.6,<2.0.0)
Requires-Dist: requests (>=2.28.2,<3.0.0)
Project-URL: Repository, https://github.com/james-allan-lloyd/slink
